nnops/__init__.py
nnops-0.0.0.dist-info/LICENSE
nnops-0.0.0.dist-info/METADATA
nnops-0.0.0.dist-info/WHEEL
nnops-0.0.0.dist-info/top_level.txt
nnops-0.0.0.dist-info/RECORD
