Metadata-Version: 2.1
Name: nnops
Version: 0.0.0
Summary: Neural Network Operators
Home-page: https://github.com/JiauZhang/nnops
Author: JiauZhang
Author-email: jiauzhang@163.com
License: MIT
Keywords: Deep Learning,Neural Network Operators,Artificial Intelligence
Classifier: Intended Audience :: Developers
Classifier: Topic :: Scientific/Engineering :: Artificial Intelligence
Classifier: License :: OSI Approved :: MIT License
Classifier: Programming Language :: Python :: 3.8
License-File: LICENSE
